README.md
setup.py
aniposelib_freemocap/__init__.py
aniposelib_freemocap/boards.py
aniposelib_freemocap/cameras.py
aniposelib_freemocap/utils.py
aniposelib_freemocap.egg-info/PKG-INFO
aniposelib_freemocap.egg-info/SOURCES.txt
aniposelib_freemocap.egg-info/dependency_links.txt
aniposelib_freemocap.egg-info/requires.txt
aniposelib_freemocap.egg-info/top_level.txt