Metadata-Version: 2.1
Name: aniposelib-freemocap
Version: 0.0.1
Summary: A fork of `lambdaloop/aniposelib` to make more compatible with the FreeMoCap system
Home-page: https://github.com/jonmatthis/aniposelib
Author: Pierre Karashchuk
Author-email: krchtchk@gmail.com
License: UNKNOWN
Platform: UNKNOWN
Classifier: Programming Language :: Python :: 3
Classifier: License :: OSI Approved :: BSD License
Classifier: Intended Audience :: Science/Research
Classifier: Topic :: Scientific/Engineering
Classifier: Topic :: Scientific/Engineering :: Image Recognition
Provides-Extra: full
